dsdatabase/__init__.py
dsdatabase/config.py
dsdatabase/db.py
dsdatabase-0.1.0.dist-info/LICENSE
dsdatabase-0.1.0.dist-info/METADATA
dsdatabase-0.1.0.dist-info/WHEEL
dsdatabase-0.1.0.dist-info/RECORD
