Metadata-Version: 2.1
Name: dsdatabase
Version: 0.1.0
Summary: DesignSafe relational database connection scripts
Author: Scott Brandenberg
Author-email: sjbrandenberg@ucla.edu
Requires-Python: >=3.9
Classifier: Programming Language :: Python :: 3
Classifier: Programming Language :: Python :: 3.9
Classifier: Programming Language :: Python :: 3.10
Classifier: Programming Language :: Python :: 3.11
Classifier: Programming Language :: Python :: 3.12
Requires-Dist: numpy (>=1.24.0,<2.0.0)
Requires-Dist: pandas (>=2.1.3,<3.0.0)
Requires-Dist: pymysql (>=1.1.0,<2.0.0)
Requires-Dist: sqlalchemy (>=2.0.23,<3.0.0)
